antchain_sdk_ak_a050edd0f07344eabd879166e7187ce5/__init__.py
antchain_sdk_ak_a050edd0f07344eabd879166e7187ce5/client.py
antchain_sdk_ak_a050edd0f07344eabd879166e7187ce5/models.py
antchain_ak_a050edd0f07344eabd879166e7187ce5-1.0.1.dist-info/LICENSE
antchain_ak_a050edd0f07344eabd879166e7187ce5-1.0.1.dist-info/METADATA
antchain_ak_a050edd0f07344eabd879166e7187ce5-1.0.1.dist-info/WHEEL
antchain_ak_a050edd0f07344eabd879166e7187ce5-1.0.1.dist-info/top_level.txt
antchain_ak_a050edd0f07344eabd879166e7187ce5-1.0.1.dist-info/RECORD
